scrapy_block_inspector/__init__.py
scrapy_block_inspector/_version.py
scrapy_block_inspector/exceptions.py
scrapy_block_inspector/spidermiddlewares/__init__.py
scrapy_block_inspector/spidermiddlewares/block_inspector.py
scrapy_block_inspector/utils/__init__.py
scrapy_block_inspector/utils/inspect_block_google_recaptcha.py
scrapy_block_inspector-0.0.2.dist-info/DESCRIPTION.rst
scrapy_block_inspector-0.0.2.dist-info/METADATA
scrapy_block_inspector-0.0.2.dist-info/RECORD
scrapy_block_inspector-0.0.2.dist-info/WHEEL
scrapy_block_inspector-0.0.2.dist-info/metadata.json
scrapy_block_inspector-0.0.2.dist-info/top_level.txt
